bball_sim_v2/__init__.py
bball_sim_v2/main.py
bball_sim_v2-0.1.0.dist-info/METADATA
bball_sim_v2-0.1.0.dist-info/WHEEL
bball_sim_v2-0.1.0.dist-info/entry_points.txt
bball_sim_v2-0.1.0.dist-info/RECORD
